SU2xSU2/SU2_mat_routines.py
SU2xSU2/SU2xSU2.py
SU2xSU2/__init__.py
SU2xSU2/analysis.py
SU2xSU2/calibrate_paras.py
SU2xSU2/correlations.py
SU2xSU2/mytests.py
SU2xSU2/plotting.py
SU2xSU2/scientific.mplstyle
SU2xSU2-2.dist-info/METADATA
SU2xSU2-2.dist-info/WHEEL
SU2xSU2-2.dist-info/top_level.txt
SU2xSU2-2.dist-info/RECORD
