Metadata-Version: 2.1
Name: SU2xSU2
Version: 2
Summary: Hybrid Monte Carlo with Fourier Acceleration simulation package for the N=2 Principal Chiral model.
Download-URL: https://pypi.org/project/SU2xSU2/
Author: Julian Wack
Author-email: julianfriedrichwack@gmail.com
License: MIT
Project-URL: Source, https://github.com/JulianWack/SU2xSU2
Project-URL: Documentation, https://su2xsu2.readthedocs.io/
Keywords: Hybrid Monte Carlo,Fourier Acceleration,Principal Chiral model
Platform: any
Classifier: Programming Language :: Python :: 3
Classifier: License :: OSI Approved :: MIT License
Classifier: Operating System :: OS Independent
Classifier: Intended Audience :: Science/Research
Classifier: Topic :: Scientific/Engineering
Classifier: Topic :: Scientific/Engineering :: Physics
Requires-Python: >=3.11.4
Requires-Dist: numpy
Requires-Dist: matplotlib
Requires-Dist: scipy
